.gitignore
CHANGES.rst
LICENCE.GPL
LICENCE.rst
MANIFEST.in
README.rst
setup.cfg
setup.py
wmowonen/__init__.py
wmowonen.theme.egg-info/PKG-INFO
wmowonen.theme.egg-info/SOURCES.txt
wmowonen.theme.egg-info/dependency_links.txt
wmowonen.theme.egg-info/entry_points.txt
wmowonen.theme.egg-info/namespace_packages.txt
wmowonen.theme.egg-info/not-zip-safe
wmowonen.theme.egg-info/requires.txt
wmowonen.theme.egg-info/top_level.txt
wmowonen/theme/__init__.py
wmowonen/theme/configure.zcml
wmowonen/theme/interfaces.py
wmowonen/theme/patches.py
wmowonen/theme/tests.py
wmowonen/theme/browser/__init__.py
wmowonen/theme/browser/configure.zcml
wmowonen/theme/browser/virtualTreeCategories.py
wmowonen/theme/dev/gruntfile.js
wmowonen/theme/dev/package.json
wmowonen/theme/dev/js/app/app.js
wmowonen/theme/dev/less/main.less
wmowonen/theme/dev/less/_include/aside.less
wmowonen/theme/dev/less/_include/body.less
wmowonen/theme/dev/less/_include/footer.less
wmowonen/theme/dev/less/_include/forms.less
wmowonen/theme/dev/less/_include/gov_view.less
wmowonen/theme/dev/less/_include/header.less
wmowonen/theme/dev/less/_include/homepage.less
wmowonen/theme/dev/less/_include/mixins.less
wmowonen/theme/dev/less/_include/search.less
wmowonen/theme/dev/less/_include/variables.less
wmowonen/theme/dev/template/endpage.html
wmowonen/theme/dev/template/homepage.html
wmowonen/theme/dev/template/page.html
wmowonen/theme/dev/template/search.html
wmowonen/theme/dev/template/startpage.html
wmowonen/theme/docs/html-snippets.html
wmowonen/theme/locales/nl/__init__.py
wmowonen/theme/locales/nl/LC_MESSAGES/.DS_Store
wmowonen/theme/locales/nl/LC_MESSAGES/README.txt
wmowonen/theme/locales/nl/LC_MESSAGES/raptus.mailchimp.po
wmowonen/theme/portlets/__init__.py
wmowonen/theme/portlets/configure.zcml
wmowonen/theme/portlets/extendedCollection.pt
wmowonen/theme/portlets/extendedCollection.py
wmowonen/theme/profiles/default/browserlayer.xml
wmowonen/theme/profiles/default/cssregistry.xml
wmowonen/theme/profiles/default/jsregistry.xml
wmowonen/theme/profiles/default/metadata.xml
wmowonen/theme/profiles/default/portlets.xml
wmowonen/theme/profiles/default/propertiestool.xml
wmowonen/theme/profiles/default/theme.xml
wmowonen/theme/profiles/default/tinymce.xml
wmowonen/theme/static/homepage.html
wmowonen/theme/static/index.html
