Metadata-Version: 1.0
Name: wmowonen.theme
Version: 0.9
Summary: Theme for WMO Wonen NH (2014)
Home-page: http://www.fourdigits.nl
Author: Four Digits
Author-email: info@fourdigits.nl
License: GPL version 2
Platform: UNKNOWN
Classifier: Framework :: Plone
Classifier: Programming Language :: Python
